oommfpy/__about__.py
oommfpy/__init__.py
oommfpy/oommfpy.py
oommfpy/tools/__init__.py
oommfpy/tools/clib/clib.c
oommfpy/tools/clib/clib.h
oommfpy/tools/clib/clib.pyx
oommfpy/tools/clib/vtk_writer.c
oommfpy/tools/clib.cpython-311-x86_64-linux-gnu.so
oommfpy/tools/omf2vtk.py
oommfpy/tools/plot_omf.py
oommfpy/tools/plot_slices.py
oommfpy/tools/plot_tools.py
oommfpy-1.4.dist-info/LICENSE
oommfpy-1.4.dist-info/METADATA
oommfpy-1.4.dist-info/WHEEL
oommfpy-1.4.dist-info/entry_points.txt
oommfpy-1.4.dist-info/RECORD
