Metadata-Version: 2.1
Name: oommfpy
Version: 1.4
Summary: Minimal Python lib to process OOMMF format output files
Home-page: https://github.com/davidcortesortuno/oommfpy
License: BSD-2-Clause
Keywords: oommf,omf,python
Author: David Cortés-Ortuño
Author-email: d.i.cortes@uu.nl
Requires-Python: >=3.10,<3.13
Classifier: License :: OSI Approved :: BSD License
Classifier: Programming Language :: Python :: 3
Classifier: Programming Language :: Python :: 3.10
Classifier: Programming Language :: Python :: 3.11
Classifier: Programming Language :: Python :: 3.12
Requires-Dist: Cython (>=3.0.0,<4.0.0)
Requires-Dist: click (>=8.1.0,<9.0.0)
Requires-Dist: matplotlib (>=3.7.0,<4.0.0)
Requires-Dist: numpy (>=2.0.0,<3.0.0)
Requires-Dist: scipy (>=1.10.0,<2.0.0)
Project-URL: Repository, https://github.com/davidcortesortuno/oommfpy
